{
  "posts": [
    {
      "id": 1,
      "title": "Task 1",
      "description": "Description for Task 1",
      "task_status": "todo",
      "tags": [
        "Personal",
        "Official"
      ],
      "subTasks": [
        {
          "subTaskTitle": "Hello",
          "status": false
        }
      ],
      "tasks_status": "in-progess"
    },
    {
      "id": 2,
      "title": "Task 2",
      "description": "Description for Task 2",
      "task_status": "in-progress",
      "tags": [
        "Official"
      ],
      "subTasks": [
        {
          "subTaskTitle": "Task2:Sub Task 1",
          "status": true
        },
        {
          "subTaskTitle": "Task2:Sub Task 2",
          "status": false
        }
      ],
      "tasks_status": "todo"
    },
    {
      "id": 3,
      "title": "Task 3",
      "description": "Description for Task 3",
      "task_status": "done",
      "tags": [
        "Others"
      ],
      "subTasks": [
        {
          "subTaskTitle": "Task3:Sub Task 1",
          "status": false
        },
        {
          "subTaskTitle": "Task3:Sub Task 2",
          "status": false
        }
      ]
    },
    {
      "id": 4,
      "title": "hellow world",
      "description": "hello world",
      "task_status": "todo",
      "tags": [
        "Personal"
      ],
      "subTasks": [
        {
          "subTaskTitle": "Task4:Sub Task 1",
          "status": true
        },
        {
          "subTaskTitle": "Task4:Sub Task 2",
          "status": false
        }
      ]
    }
  ]
}